{
    "title": "Uday scheme helps discom bring losses down 70% to Rs 170 bn: Deutsche Bank",
    "link": "https://www.business-standard.com/article/economy-policy/uday-scheme-helps-discom-bring-losses-down-70-to-rs-170-bn-deutsche-bank-118061800896_1.html",
    "pubDate": "Mon, 18 Jun 2018 19:45:00 +0530",
    "content": "The UDAY scheme has helped debt laden discoms reduce annual losses by 70 per cent to around Rs 17,350 crore in last two years, according to the Deutsche Bank Market Research report.\r\nThe scheme for restructuring power distribution companies has also helped them cut aggregate technical and commercial losses by 5 per cent.\r\nThe report said however that the net results of UDAY scheme have not been keeping pace with the stringent targeted trajectory.\r\nIt also said that the gap between ACS (actual cost of supply of power) and  ARR (Cost & Tariff rate) has reduced to Rs 0.24/kWh or by 57 per cent over two years.\r\nThe government had launched Uday reforms for the power distribution sector in November 2015, to turn them around from deep financial and operational losses.\r\nAt that time the accumulated losses of these discoms amounted to Rs 4.3 lakh crore with annual incremental losses of Rs 60,000 crore.\r\nIt said that electricity demand revival is partly showing up in elevated exchange tariffs as",
    "contentSnippet": "The UDAY scheme has helped debt laden discoms reduce annual losses by 70 per cent to around Rs 17,350 crore in last two years, according to the Deutsche Bank Market Research report.\r\nThe scheme for restructuring power distribution companies has also helped them cut aggregate technical and commercial losses by 5 per cent.\r\nThe report said however that the net results of UDAY scheme have not been keeping pace with the stringent targeted trajectory.\r\nIt also said that the gap between ACS (actual cost of supply of power) and  ARR (Cost & Tariff rate) has reduced to Rs 0.24/kWh or by 57 per cent over two years.\r\nThe government had launched Uday reforms for the power distribution sector in November 2015, to turn them around from deep financial and operational losses.\r\nAt that time the accumulated losses of these discoms amounted to Rs 4.3 lakh crore with annual incremental losses of Rs 60,000 crore.\r\nIt said that electricity demand revival is partly showing up in elevated exchange tariffs as",
    "guid": "https://www.business-standard.com/article/economy-policy/uday-scheme-helps-discom-bring-losses-down-70-to-rs-170-bn-deutsche-bank-118061800896_1.html",
    "isoDate": "2018-06-18T14:15:00.000Z",
    "sentiment": {
        "score": -1,
        "comparative": -0.07142857142857142,
        "tokens": [
            "uday",
            "scheme",
            "helps",
            "discom",
            "bring",
            "losses",
            "down",
            "70",
            "to",
            "rs",
            "170",
            "bn",
            "deutsche",
            "bank"
        ],
        "words": [
            "losses",
            "helps"
        ],
        "positive": [
            "helps"
        ],
        "negative": [
            "losses"
        ]
    },
    "article": {},
    "adjectives": [
        "commercial",
        "two",
        "cut",
        "reduced",
        "actual",
        "according",
        "accumulated",
        "incremental",
        "stringent",
        "financial",
        "last",
        "60",
        "70",
        "technical",
        "elevated",
        "operational",
        "down",
        "170",
        "laden",
        "annual",
        "17",
        "aggregate",
        "net",
        "24",
        "57",
        "deep"
    ],
    "nouns": [
        "revival",
        "Market",
        "commercial",
        "two",
        "rate",
        "report",
        "cut",
        "trajectory",
        "Bank",
        "years",
        "government",
        "sector",
        "demand",
        "pace",
        "lakh",
        "showing",
        "supply",
        "cent",
        "crore",
        "distribution",
        "Tariff",
        "power",
        "Research",
        "last",
        "60",
        "70",
        "electricity",
        "elevated",
        "technical",
        "cost",
        "Cost",
        "time",
        "exchange",
        "keeping",
        "down",
        "scheme",
        "losses",
        "debt",
        "annual",
        "17",
        "aggregate",
        "net",
        "It",
        "24",
        "November",
        "turn",
        "deep",
        "gap",
        "At"
    ],
    "verbs": [
        "Market",
        "rate",
        "report",
        "cut",
        "Bank",
        "reduce",
        "demand",
        "pace",
        "supply",
        "Tariff",
        "power",
        "Research",
        "last",
        "cost",
        "Cost",
        "time",
        "exchange",
        "down",
        "scheme",
        "bring",
        "laden",
        "aggregate",
        "net",
        "gap",
        "turn"
    ]
}