{
    "title": "Govt counters UN report on fall in FDI, claims it rose to $61.96 bn in FY18",
    "link": "https://www.business-standard.com/article/economy-policy/govt-counters-un-report-on-fall-in-fdi-claims-it-rose-to-61-96-bn-in-fy18-118060800933_1.html",
    "pubDate": "Sat, 09 Jun 2018 00:47:00 +0530",
    "content": "Two days after a report by the United Nations Conference On Trade and Development (UNCTAD) showed that foreign direct investments into India fell by $ 4.5 billion in 2017, the government on Friday pointed to latest statistics to say that FDI has actually risen.Addressing the media on four years of the Modi government, Ramesh Abhishek, Secretary at the Department of Industrial Policy and Promotion pointed out that FDI rose to $ 61.96 billion in 2017-18 as compared to $ 60.08 billion in the year before. FDI in the first four years of the Narendra Modi government rose to $222.75 billion compared to $152 billion in the previous four years, Abhishek added.While the government compiles FDI statistics over the financial year period, the UNCTAD report calculated on a calendar year basis to show that inbound equity investments fell from $ 44.48 billion to $ 39.91 billion in 2017.All investments welcome but Apple hasn't called so farCommerce and industry minister Suresh Prabhu also reiterated ..",
    "contentSnippet": "Two days after a report by the United Nations Conference On Trade and Development (UNCTAD) showed that foreign direct investments into India fell by $ 4.5 billion in 2017, the government on Friday pointed to latest statistics to say that FDI has actually risen.Addressing the media on four years of the Modi government, Ramesh Abhishek, Secretary at the Department of Industrial Policy and Promotion pointed out that FDI rose to $ 61.96 billion in 2017-18 as compared to $ 60.08 billion in the year before. FDI in the first four years of the Narendra Modi government rose to $222.75 billion compared to $152 billion in the previous four years, Abhishek added.While the government compiles FDI statistics over the financial year period, the UNCTAD report calculated on a calendar year basis to show that inbound equity investments fell from $ 44.48 billion to $ 39.91 billion in 2017.All investments welcome but Apple hasn't called so farCommerce and industry minister Suresh Prabhu also reiterated ..",
    "guid": "https://www.business-standard.com/article/economy-policy/govt-counters-un-report-on-fall-in-fdi-claims-it-rose-to-61-96-bn-in-fy18-118060800933_1.html",
    "isoDate": "2018-06-08T19:17:00.000Z",
    "sentiment": {
        "score": 1,
        "comparative": 0.0625,
        "tokens": [
            "govt",
            "counters",
            "un",
            "report",
            "on",
            "fall",
            "in",
            "fdi",
            "claims",
            "it",
            "rose",
            "to",
            "6196",
            "bn",
            "in",
            "fy18"
        ],
        "words": [
            "rose"
        ],
        "positive": [
            "rose"
        ],
        "negative": []
    },
    "article": {},
    "adjectives": [
        "Industrial",
        "risen",
        "first",
        "financial",
        "pointed",
        "Two",
        "four",
        "foreign",
        "billion",
        "61",
        "96",
        "18",
        "direct",
        "60",
        "previous",
        "rose",
        "United",
        "On",
        "fell",
        "latest",
        "75",
        "calculated",
        "inbound",
        "44",
        "48",
        "39",
        "91",
        "All",
        "welcome"
    ],
    "nouns": [
        "India",
        "industry",
        "years",
        "year",
        "government",
        "Friday",
        "Conference",
        "first",
        "statistics",
        "days",
        "Promotion",
        "Two",
        "Policy",
        "fall",
        "Secretary",
        "four",
        "Apple",
        "report",
        "Department",
        "Development",
        "period",
        "billion",
        "18",
        "60",
        "UN",
        "rose",
        "Trade",
        "show",
        "fell",
        "latest",
        "say",
        "While",
        "calendar",
        "basis",
        "so",
        "minister",
        "welcome",
        "equity"
    ],
    "verbs": [
        "fall",
        "report",
        "direct",
        "Trade",
        "show",
        "fell",
        "say",
        "calendar",
        "welcome",
        "minister"
    ]
}