{
    "title": "RBI's revised framework on stressed assets resolution hits IOB bottom line",
    "link": "https://www.business-standard.com/article/companies/rbi-s-revised-framework-on-stressed-assets-resolution-hits-iob-bottom-line-118053000593_1.html",
    "pubDate": "Wed, 30 May 2018 17:41:00 +0530",
    "content": "Net loss of Indian Overseas Bank has widened to Rs 36.06 billion during the quarter ended March 31, 2018, as compared to Rs 6.46 billion during the same quarter last year, owing to higher provisioning as per the revised regulatory framework by RBI.The increase in losses is mainly due to provisioning requirements including higher provisions as per RBI guidelines on revised framework on Resolution of Stressed Assets, said the Bank.Following the revised framework, the Bank has classified the specific restructured accounts in accordance with extant Income Recognition and Asset Classification (IRAC) norms and made a provision of Rs 7.99 billion towards such accounts during the current quarter.While the total recovery during the quarter was at Rs 57.26 billion as against the recovery of Rs 27.29 billion during quarter ended March 2017 while the total slippage for quarter ended March 2018 stood at Rs 98.68 billion mainly on account of theimpact of RBI guidelines on revised framework on ...",
    "contentSnippet": "Net loss of Indian Overseas Bank has widened to Rs 36.06 billion during the quarter ended March 31, 2018, as compared to Rs 6.46 billion during the same quarter last year, owing to higher provisioning as per the revised regulatory framework by RBI.The increase in losses is mainly due to provisioning requirements including higher provisions as per RBI guidelines on revised framework on Resolution of Stressed Assets, said the Bank.Following the revised framework, the Bank has classified the specific restructured accounts in accordance with extant Income Recognition and Asset Classification (IRAC) norms and made a provision of Rs 7.99 billion towards such accounts during the current quarter.While the total recovery during the quarter was at Rs 57.26 billion as against the recovery of Rs 27.29 billion during quarter ended March 2017 while the total slippage for quarter ended March 2018 stood at Rs 98.68 billion mainly on account of theimpact of RBI guidelines on revised framework on ...",
    "guid": "https://www.business-standard.com/article/companies/rbi-s-revised-framework-on-stressed-assets-resolution-hits-iob-bottom-line-118053000593_1.html",
    "isoDate": "2018-05-30T12:11:00.000Z",
    "sentiment": {
        "score": 2,
        "comparative": 0.18181818181818182,
        "tokens": [
            "rbi's",
            "revised",
            "framework",
            "on",
            "stressed",
            "assets",
            "resolution",
            "hits",
            "iob",
            "bottom",
            "line"
        ],
        "words": [
            "resolution",
            "assets",
            "stressed"
        ],
        "positive": [
            "resolution",
            "assets"
        ],
        "negative": [
            "stressed"
        ]
    },
    "article": {},
    "adjectives": [
        "Indian",
        "regulatory",
        "billion",
        "stressed",
        "Stressed",
        "57",
        "revised",
        "higher",
        "current",
        "68",
        "27",
        "Overseas",
        "ended",
        "98",
        "specific",
        "last",
        "bottom",
        "Net",
        "36",
        "31",
        "46",
        "owing",
        "due",
        "Following",
        "classified",
        "extant",
        "made",
        "99",
        "total",
        "26",
        "29"
    ],
    "verbs": [
        "March",
        "increase",
        "provision",
        "account",
        "Bank",
        "line",
        "last",
        "bottom",
        "Net",
        "quarter",
        "total"
    ]
}