{
    "title": "Bitcoin scam: Second charge sheet filed against Amit Bhardwaj",
    "link": "https://www.business-standard.com/article/news-ani/bitcoin-scam-second-charge-sheet-filed-against-amit-bhardwaj-118061401169_1.html",
    "pubDate": "Thu, 14 Jun 2018 20:20:28 +0530",
    "content": "The Pune Police's Cyber Cell on Thursday filed a second charge sheet against investor Amit Bhardwaj in connection with two crypto-currency fraud cases.According to the Pune Police's investigation so far, no involvement of any celebrity has been found in the scam.Earlier on June 5, actor Shilpa Shetty's husband Raj Kundra was summoned by the Enforcement Directorate in connection with a Bitcoin scam after alleged links with Bhardwaj were discovered.According to media reports, Bhardwaj had started the country's first online marketplace which accepted bitcoins. He had also started bitcoin mining start-ups.He reportedly lured in investors with promises of hefty returns, assuring them of access to the bitcoin mining system.Bhardwaj was arrested in New Delhi on April 5. He was then brought to Pune for investigations in the two cases.Earlier on June 6, police had busted a crypto-currency racket and arrested one in Maharashtra's Thane.",
    "contentSnippet": "The Pune Police's Cyber Cell on Thursday filed a second charge sheet against investor Amit Bhardwaj in connection with two crypto-currency fraud cases.According to the Pune Police's investigation so far, no involvement of any celebrity has been found in the scam.Earlier on June 5, actor Shilpa Shetty's husband Raj Kundra was summoned by the Enforcement Directorate in connection with a Bitcoin scam after alleged links with Bhardwaj were discovered.According to media reports, Bhardwaj had started the country's first online marketplace which accepted bitcoins. He had also started bitcoin mining start-ups.He reportedly lured in investors with promises of hefty returns, assuring them of access to the bitcoin mining system.Bhardwaj was arrested in New Delhi on April 5. He was then brought to Pune for investigations in the two cases.Earlier on June 6, police had busted a crypto-currency racket and arrested one in Maharashtra's Thane.",
    "guid": "https://www.business-standard.com/article/news-ani/bitcoin-scam-second-charge-sheet-filed-against-amit-bhardwaj-118061401169_1.html",
    "isoDate": "2018-06-14T14:50:28.000Z",
    "sentiment": {
        "score": -2,
        "comparative": -0.2222222222222222,
        "tokens": [
            "bitcoin",
            "scam",
            "second",
            "charge",
            "sheet",
            "filed",
            "against",
            "amit",
            "bhardwaj"
        ],
        "words": [
            "scam"
        ],
        "positive": [],
        "negative": [
            "scam"
        ]
    },
    "article": {},
    "adjectives": [
        "far",
        "New",
        "Second",
        "second",
        "two",
        "one",
        "found",
        "discovered",
        "Earlier",
        "According",
        "accepted",
        "no",
        "alleged",
        "first",
        "online",
        "hefty",
        "assuring",
        "busted"
    ],
    "nouns": [
        "connection",
        "charge",
        "Thursday",
        "far",
        "marketplace",
        "Second",
        "second",
        "April",
        "two",
        "start",
        "one",
        "found",
        "investor",
        "investigation",
        "involvement",
        "fraud",
        "June",
        "currency",
        "Police",
        "police",
        "sheet",
        "scam",
        "Cell",
        "celebrity",
        "access",
        "so",
        "no",
        "actor",
        "Raj",
        "Enforcement",
        "Directorate",
        "links",
        "husband",
        "country",
        "first",
        "He",
        "mining",
        "system",
        "Delhi",
        "racket",
        "Maharashtra",
        "Thane"
    ],
    "verbs": [
        "charge",
        "Second",
        "second",
        "start",
        "found",
        "scam",
        "sheet",
        "Police",
        "police",
        "access",
        "husband",
        "racket"
    ]
}