{
    "title": "Bitcoin scam: Raj Kundra summoned by ED",
    "link": "https://www.business-standard.com/article/news-ani/bitcoin-scam-raj-kundra-summoned-by-ed-118060500474_1.html",
    "pubDate": "Tue, 05 Jun 2018 14:00:02 +0530",
    "content": "Businessman and actor Shilpa Shetty's husband Raj Kundra, was on Tuesday summoned by the Enforcement Directorate (ED) in connection with the Bitcoin scam.Kundra's name turned up in the report following alleged links with Bitcoin scamster Amit Bhardwaj. He is currently being questioned in the ED's Mumbai branch.According to media reports, Bhardwaj had started the country's first online marketplace which accepted bitcoins and had also started bitcoin mining start-ups.He reportedly lured in investors with promises of hefty returns, assuring the investors of access to the bitcoin mining system that would let them mine their own bitcoins.Kundra had allegedly promoted one of Bhardwaj's operations.In May, the Gujarat branch of Criminal Investigation Department (CID) had arrested Kirit Paladiya for stealing bitcoins from his partner.According to the police authorities, Paladiya stole 176 bitcoins worth over Rs 9 crore from his partner, Shailesh Bhatt.Also, Amreli's Superintendent of Police ...",
    "contentSnippet": "Businessman and actor Shilpa Shetty's husband Raj Kundra, was on Tuesday summoned by the Enforcement Directorate (ED) in connection with the Bitcoin scam.Kundra's name turned up in the report following alleged links with Bitcoin scamster Amit Bhardwaj. He is currently being questioned in the ED's Mumbai branch.According to media reports, Bhardwaj had started the country's first online marketplace which accepted bitcoins and had also started bitcoin mining start-ups.He reportedly lured in investors with promises of hefty returns, assuring the investors of access to the bitcoin mining system that would let them mine their own bitcoins.Kundra had allegedly promoted one of Bhardwaj's operations.In May, the Gujarat branch of Criminal Investigation Department (CID) had arrested Kirit Paladiya for stealing bitcoins from his partner.According to the police authorities, Paladiya stole 176 bitcoins worth over Rs 9 crore from his partner, Shailesh Bhatt.Also, Amreli's Superintendent of Police ...",
    "guid": "https://www.business-standard.com/article/news-ani/bitcoin-scam-raj-kundra-summoned-by-ed-118060500474_1.html",
    "isoDate": "2018-06-05T08:30:02.000Z",
    "sentiment": {
        "score": -2,
        "comparative": -0.2857142857142857,
        "tokens": [
            "bitcoin",
            "scam",
            "raj",
            "kundra",
            "summoned",
            "by",
            "ed"
        ],
        "words": [
            "scam"
        ],
        "positive": [],
        "negative": [
            "scam"
        ]
    },
    "article": {},
    "adjectives": [
        "one",
        "In",
        "According",
        "accepted",
        "worth",
        "first",
        "alleged",
        "assuring",
        "own",
        "following",
        "turned",
        "online",
        "hefty",
        "Criminal"
    ],
    "verbs": [
        "mine",
        "access",
        "report",
        "start",
        "partner",
        "husband",
        "own",
        "police",
        "Police",
        "branch",
        "scam",
        "name",
        "let"
    ]
}