{
    "title": "IIM-A, other top B-schools moot IIT-like joint placement committee",
    "link": "https://www.business-standard.com/article/management/iim-a-other-top-b-schools-moot-iit-like-joint-placement-committee-118061800806_1.html",
    "pubDate": "Tue, 19 Jun 2018 00:39:00 +0530",
    "content": "Talks are on between some of the top B-schools including Indian Institute of Management, Ahmedabad (IIM-A), IIM Bangalore, IIM Lucknow, IIM Indore, MDI Gurgaon, XLRI Jamshedpur and IIFT Delhi to form an All India B-school Placements Committee on the lines of All IITs Placement Committee. The discussion was part of the agenda at Maitri, an annual conference of placement committee members. Held at IIFT Delhi in its second edition, Maitri's first edition was held last year at IIM Ahmedabad. Being conducted by student representatives this time unlike last year, the conference also saw discussions over sharing recruiter experiences and best practices between the top B-schools.\"One of the agendas of Maitri 2018 was to discuss the formation an All India B-School Placements Committee which would perform a function similar to the existing All-IITs Placements Committee,\" the IIFT placement committee's communique stated.IITs already share their best practices and take joint placement process, ...",
    "contentSnippet": "Talks are on between some of the top B-schools including Indian Institute of Management, Ahmedabad (IIM-A), IIM Bangalore, IIM Lucknow, IIM Indore, MDI Gurgaon, XLRI Jamshedpur and IIFT Delhi to form an All India B-school Placements Committee on the lines of All IITs Placement Committee. The discussion was part of the agenda at Maitri, an annual conference of placement committee members. Held at IIFT Delhi in its second edition, Maitri's first edition was held last year at IIM Ahmedabad. Being conducted by student representatives this time unlike last year, the conference also saw discussions over sharing recruiter experiences and best practices between the top B-schools.\"One of the agendas of Maitri 2018 was to discuss the formation an All India B-School Placements Committee which would perform a function similar to the existing All-IITs Placements Committee,\" the IIFT placement committee's communique stated.IITs already share their best practices and take joint placement process, ...",
    "guid": "https://www.business-standard.com/article/management/iim-a-other-top-b-schools-moot-iit-like-joint-placement-committee-118061800806_1.html",
    "isoDate": "2018-06-18T19:09:00.000Z",
    "sentiment": {
        "score": 2,
        "comparative": 0.2222222222222222,
        "tokens": [
            "iim-a",
            "other",
            "top",
            "b-schools",
            "moot",
            "iit-like",
            "joint",
            "placement",
            "committee"
        ],
        "words": [
            "top"
        ],
        "positive": [
            "top"
        ],
        "negative": []
    },
    "article": {},
    "adjectives": [
        "Indian",
        "unlike",
        "sharing",
        "second",
        "first",
        "stated",
        "One",
        "last",
        "All",
        "similar",
        "Held",
        "held",
        "annual",
        "joint",
        "top",
        "moot",
        "best",
        "existing"
    ],
    "nouns": [
        "Indian",
        "India",
        "Management",
        "part",
        "committee",
        "Committee",
        "communique",
        "process",
        "sharing",
        "share",
        "Bangalore",
        "year",
        "second",
        "student",
        "first",
        "function",
        "placement",
        "Placement",
        "discussion",
        "form",
        "formation",
        "One",
        "last",
        "recruiter",
        "conference",
        "Institute",
        "A",
        "time",
        "school",
        "School",
        "annual",
        "Talks",
        "joint",
        "B",
        "Delhi",
        "agenda",
        "top",
        "moot",
        "Lucknow",
        "MDI",
        "edition",
        "Being",
        "saw",
        "best"
    ],
    "verbs": [
        "part",
        "process",
        "share",
        "second",
        "perform",
        "function",
        "discuss",
        "form",
        "last",
        "Institute",
        "time",
        "school",
        "School",
        "joint",
        "top",
        "moot",
        "saw",
        "best"
    ]
}